qinsilk_scm_openapi_sdk_py/__init__.py
qinsilk_scm_openapi_sdk_py/client.py
qinsilk_scm_openapi_sdk_py/exceptions.py
qinsilk_scm_openapi_sdk_py/signing.py
qinsilk_scm_openapi_sdk_py/models/__init__.py
qinsilk_scm_openapi_sdk_py/models/base.py
qinsilk_scm_openapi_sdk_py/models/brand.py
qinsilk_scm_openapi_sdk_py/models/color.py
qinsilk_scm_openapi_sdk_py/models/goods.py
qinsilk_scm_openapi_sdk_py/models/material.py
qinsilk_scm_openapi_sdk_py/models/material_type.py
qinsilk_scm_openapi_sdk_py/models/order.py
qinsilk_scm_openapi_sdk_py/models/oss.py
qinsilk_scm_openapi_sdk_py/models/ranges.py
qinsilk_scm_openapi_sdk_py/models/report.py
qinsilk_scm_openapi_sdk_py/models/season.py
qinsilk_scm_openapi_sdk_py/models/size.py
qinsilk_scm_openapi_sdk_py/models/storehouse.py
qinsilk_scm_openapi_sdk_py/models/supplier.py
qinsilk_scm_openapi_sdk_py/models/token.py
qinsilk_scm_openapi_sdk_py/models/user.py
qinsilk_scm_openapi_sdk_py/utils/__init__.py
qinsilk_scm_openapi_sdk_py/utils/dataclass_helper.py
qinsilk_scm_openapi_sdk_py/utils/serialization.py
qinsilk_scm_openapi_sdk_py/utils/type_conversion.py
tests/__init__.py
tests/conftest.py
tests/constant.py
tests/quick_test.py
tests/run_tests.py
tests/test_base.py
tests/test_brand_detail_list.py
tests/test_brand_save.py
tests/test_brand_update_delete.py
tests/test_client_token.py
tests/test_color_group.py
tests/test_color_save.py
tests/test_color_update_delete_detail_list.py
tests/test_goods_detail.py
tests/test_goods_list.py
tests/test_goods_save.py
tests/test_material.py
tests/test_material_purchase.py
tests/test_material_type.py
tests/test_oss.py
tests/test_produce_order.py
tests/test_ranges.py
tests/test_reports.py
tests/test_season_delete.py
tests/test_season_detail.py
tests/test_season_list.py
tests/test_season_save.py
tests/test_season_update.py
tests/test_size_group.py
tests/test_size_save.py
tests/test_size_update_delete_detail_list.py
tests/test_storehouse.py
tests/test_supplier.py
tests/test_user_detail_delete.py
qinsilk_scm_openapi_sdk_py-1.1.7.dist-info/METADATA
qinsilk_scm_openapi_sdk_py-1.1.7.dist-info/WHEEL
qinsilk_scm_openapi_sdk_py-1.1.7.dist-info/top_level.txt
qinsilk_scm_openapi_sdk_py-1.1.7.dist-info/RECORD
