Metadata-Version: 2.4
Name: qinsilk-scm-openapi-sdk-py
Version: 1.1.7
Summary: Qinsilk SCM OpenAPI SDK for Python
Home-page: https://github.com/qinsilk/qinsilk-starter
Author: Qinsilk
Author-email: tech@qinsilk.com
Classifier: Programming Language :: Python :: 3
Classifier: License :: OSI Approved :: MIT License
Classifier: Operating System :: OS Independent
Requires-Python: >=3.6
Requires-Dist: requests
Requires-Dist: python-dotenv
Dynamic: author
Dynamic: author-email
Dynamic: classifier
Dynamic: description
Dynamic: description-content-type
Dynamic: home-page
Dynamic: requires-dist
Dynamic: requires-python
Dynamic: summary
